{
    "Name": "Dutch Ruppersberger",
    "Profile": {
        "Public Office": {
            "Member of the U.S. House of Representativesfrom Maryland's 2nd district": {
                "Incumbent": "Incumbent",
                "Assumed office": "January 3, 2003",
                "Preceded by": "Bob Ehrlich",
                "District Info": {
                    "Median householdincome": "$80,984",
                    "Distribution": "64.1% urban,35.9% rural",
                    "Population": "780,224",
                    "Ethnicity": "80.3% ,White,11.9% ,Black,3.5% ,Hispanic,2.1% ,Asian,2.0% ,Two or more races,0.3% other"
                }
            },
            "Ranking Member of the House Intelligence Committee": {
                "In office": "January 3, 2011 – January 3, 2015",
                "Preceded by": "Pete Hoekstra",
                "Succeeded by": "Adam Schiff"
            },
            "10th Baltimore County Executive": {
                "In office": "December 5, 1994 – December 2, 2002",
                "Preceded by": "Roger B. Hayden",
                "Succeeded by": "James T. Smith Jr."
            }
        }
    },
    "UnusedVotingRecords": [],
    "VotingRecord": []
}